pyCMakeSetupTool/cmake.py
pyCMakeSetupTool/__init__.py
radfiled3d-1.2.3.dist-info/WHEEL
radfiled3d-1.2.3.dist-info/top_level.txt
radfiled3d-1.2.3.dist-info/METADATA
radfiled3d-1.2.3.dist-info/RECORD
radfiled3d-1.2.3.dist-info/licenses/LICENSE
RadFiled3D/__init__.pyi
RadFiled3D/RadFiled3D.pyi
RadFiled3D/RadFiled3D.cpython-311-x86_64-linux-gnu.so
RadFiled3D/__init__.py
RadFiled3D/utils/__init__.py
RadFiled3D/metadata/__init__.py
RadFiled3D/metadata/v1.py
RadFiled3D/pytorch/radiationfieldloader.py
RadFiled3D/pytorch/types.py
RadFiled3D/pytorch/helpers.py
RadFiled3D/pytorch/__init__.py
RadFiled3D/pytorch/datasets/radfield3d.py
RadFiled3D/pytorch/datasets/processing.py
RadFiled3D/pytorch/datasets/cartesian.py
RadFiled3D/pytorch/datasets/polar.py
RadFiled3D/pytorch/datasets/__init__.py
RadFiled3D/pytorch/datasets/base.py
