Metadata-Version: 2.4
Name: RadFiled3D
Version: 1.2.3
Summary: # RadFiled3D
Author: Felix Lehner
Author-email: felix.lehner@ptb.de
License: MIT License
Requires-Python: >=3.11
License-File: LICENSE
Requires-Dist: numpy>=2.0
Requires-Dist: rich>=13.9
Dynamic: author
Dynamic: author-email
Dynamic: description
Dynamic: description-content-type
Dynamic: license
Dynamic: license-file
Dynamic: requires-dist
Dynamic: requires-python
Dynamic: summary
